LICENSE.txt
README.md
setup.py
automl_sphinx_theme/__init__.py
automl_sphinx_theme/__version__.py
automl_sphinx_theme/conf.py
automl_sphinx_theme/docs-navbar.html
automl_sphinx_theme/docs-sidebar.html
automl_sphinx_theme/footer.html
automl_sphinx_theme/gc.html
automl_sphinx_theme/icon-links.html
automl_sphinx_theme/layout.html
automl_sphinx_theme/layout.py
automl_sphinx_theme/search-field.html
automl_sphinx_theme/theme.conf
automl_sphinx_theme/title.html
automl_sphinx_theme/translator.py
automl_sphinx_theme/version-switcher.html
automl_sphinx_theme.egg-info/PKG-INFO
automl_sphinx_theme.egg-info/PKG-INFO 2
automl_sphinx_theme.egg-info/SOURCES.txt
automl_sphinx_theme.egg-info/dependency_links.txt
automl_sphinx_theme.egg-info/entry_points.txt
automl_sphinx_theme.egg-info/not-zip-safe
automl_sphinx_theme.egg-info/requires 2.txt
automl_sphinx_theme.egg-info/requires.txt
automl_sphinx_theme.egg-info/top_level.txt
automl_sphinx_theme/static/webpack-macros.html
automl_sphinx_theme/static/css/custom.css
automl_sphinx_theme/static/css/index.ac9c05f7c49ca1e1f876c6e36360ea26.css
automl_sphinx_theme/static/css/theme.css
automl_sphinx_theme/static/js/index.9ea38e314b9e6d9dab77.js
automl_sphinx_theme/static/vendor/fontawesome/5.13.0/LICENSE.txt
automl_sphinx_theme/static/vendor/fontawesome/5.13.0/css/all.min.css
automl_sphinx_theme/static/vendor/fontawesome/5.13.0/webfonts/fa-brands-400.eot
automl_sphinx_theme/static/vendor/fontawesome/5.13.0/webfonts/fa-brands-400.svg
automl_sphinx_theme/static/vendor/fontawesome/5.13.0/webfonts/fa-brands-400.ttf
automl_sphinx_theme/static/vendor/fontawesome/5.13.0/webfonts/fa-brands-400.woff
automl_sphinx_theme/static/vendor/fontawesome/5.13.0/webfonts/fa-brands-400.woff2
automl_sphinx_theme/static/vendor/fontawesome/5.13.0/webfonts/fa-regular-400.eot
automl_sphinx_theme/static/vendor/fontawesome/5.13.0/webfonts/fa-regular-400.svg
automl_sphinx_theme/static/vendor/fontawesome/5.13.0/webfonts/fa-regular-400.ttf
automl_sphinx_theme/static/vendor/fontawesome/5.13.0/webfonts/fa-regular-400.woff
automl_sphinx_theme/static/vendor/fontawesome/5.13.0/webfonts/fa-regular-400.woff2
automl_sphinx_theme/static/vendor/fontawesome/5.13.0/webfonts/fa-solid-900.eot
automl_sphinx_theme/static/vendor/fontawesome/5.13.0/webfonts/fa-solid-900.svg
automl_sphinx_theme/static/vendor/fontawesome/5.13.0/webfonts/fa-solid-900.ttf
