Metadata-Version: 2.1
Name: automl-sphinx-theme
Version: 0.2.0
Summary: AutoML Theme for Sphinx
Home-page: https://github.com/automl/automl_sphinx_theme
Author: René Sass and Edward Bergman
Author-email: sass@tnt.uni-hannover.de
License: MIT
Platform: UNKNOWN
Classifier: Programming Language :: Python :: 3.7
Classifier: Programming Language :: Python :: 3.8
Classifier: Programming Language :: Python :: 3.9
Classifier: Programming Language :: Python :: 3.10
Classifier: Topic :: Documentation
Classifier: Topic :: Software Development :: Documentation
Requires-Python: >=3.7
Provides-Extra: dev
License-File: LICENSE.txt
